notations.py
notations-0.2.0.dist-info/LICENSE
notations-0.2.0.dist-info/WHEEL
notations-0.2.0.dist-info/METADATA
notations-0.2.0.dist-info/RECORD
