Metadata-Version: 2.1
Name: notations
Version: 0.2.0
Summary: Notations
Home-page: https://github.com/tonybaloney/notations
License: UNKNOWN
Author: Anthony Shaw
Author-email: anthonyshaw@apache.org
Classifier: License :: OSI Approved :: Apache Software License
